Color_Console/Color_Console.py
Color_Console/__init__.py
Color_Console/setup.py
Color_Console-10.0.dist-info/LICENSE.txt
Color_Console-10.0.dist-info/METADATA
Color_Console-10.0.dist-info/WHEEL
Color_Console-10.0.dist-info/top_level.txt
Color_Console-10.0.dist-info/RECORD
