Metadata-Version: 2.1
Name: Color_Console
Version: 10.0
Summary: Comprehensive Utility Library for changing the color of text and background of a python console.
Home-page: https://github.com/SayadPervez/Color_Console
Author: Sayad Pervez
Author-email: pervez2504@gmail.com
License: UNKNOWN
Platform: UNKNOWN
Classifier: Programming Language :: Python :: 3
Classifier: License :: OSI Approved :: MIT License
Classifier: Operating System :: OS Independent
